veil/__init__.py
veil/_rust_core.cpython-312-x86_64-linux-gnu.so
veil/assets.py
veil/client.py
veil/solana_client.py
veil/token_utils.py
veil/types.py
veil/utils.py
veil_solana-0.1.1.dist-info/METADATA
veil_solana-0.1.1.dist-info/WHEEL
veil_solana-0.1.1.dist-info/licenses/LICENSE
veil_solana-0.1.1.dist-info/RECORD
