Metadata-Version: 2.4
Name: veil-solana
Version: 0.1.1
Classifier: Intended Audience :: Developers
Classifier: License :: OSI Approved :: MIT License
Classifier: Programming Language :: Python :: 3.12
Classifier: Programming Language :: Rust
Classifier: Topic :: Security :: Cryptography
Classifier: Topic :: Software Development :: Libraries :: Python Modules
Requires-Dist: solana>=0.30.0
Requires-Dist: solders>=0.18.0
Requires-Dist: anchorpy>=0.18.0
Requires-Dist: base58>=2.1.1
Requires-Dist: pynacl>=1.5.0
Requires-Dist: pytest>=7.4.0 ; extra == 'dev'
Requires-Dist: pytest-asyncio>=0.21.0 ; extra == 'dev'
Requires-Dist: pytest-cov>=4.1.0 ; extra == 'dev'
Requires-Dist: black>=23.0.0 ; extra == 'dev'
Requires-Dist: mypy>=1.0.0 ; extra == 'dev'
Requires-Dist: ruff>=0.1.0 ; extra == 'dev'
Requires-Dist: ipython>=8.0.0 ; extra == 'dev'
Provides-Extra: dev
License-File: LICENSE
Summary: Privacy SDK for Solana with zkSNARK-powered transactions - Python interface with Rust cryptographic backbone
Keywords: solana,privacy,zksnark,zero-knowledge,defi,sdk
Author-email: Veil Team <dev@veil-sdk.com>
License: MIT
Requires-Python: >=3.12
Project-URL: Homepage, https://github.com/veil-solana/veil
Project-URL: Documentation, https://veil-sdk.com/docs/getting-started/overview
Project-URL: Repository, https://github.com/veil-solana/veil
Project-URL: Issues, https://github.com/veil-solana/veil/issues
